kognic/auth/__init__.py
kognic/auth/_version.py
kognic/auth/credentials_parser.py
kognic/auth/base/__init__.py
kognic/auth/base/auth_client.py
kognic/auth/httpx/__init__.py
kognic/auth/httpx/async_client.py
kognic/auth/requests/__init__.py
kognic/auth/requests/auth_session.py
kognic_auth-3.8.0.dist-info/METADATA
kognic_auth-3.8.0.dist-info/WHEEL
kognic_auth-3.8.0.dist-info/top_level.txt
kognic_auth-3.8.0.dist-info/RECORD
