Metadata-Version: 2.4
Name: kognic-auth
Version: 3.8.0
Summary: Kognic Authentication
Author-email: Kognic <michel.edkrantz@kognic.com>
License: MIT
Project-URL: homepage, https://github.com/annotell/kognic-auth-python
Keywords: Kognic,API
Classifier: Development Status :: 5 - Production/Stable
Classifier: License :: OSI Approved :: MIT License
Classifier: Intended Audience :: Developers
Classifier: Programming Language :: Python :: 3
Requires-Python: >=3.8
Requires-Dist: authlib<1.7,>=0.14.1
Provides-Extra: httpx
Requires-Dist: httpx<1,>=0.20; extra == "httpx"
Provides-Extra: requests
Requires-Dist: requests<3,>=2.20; extra == "requests"
Provides-Extra: full
Requires-Dist: httpx<1,>=0.20; extra == "full"
Requires-Dist: requests<3,>=2.20; extra == "full"
